b3_data/__init__.py
b3_data/download.py
b3_data/main.py
b3_data-0.2.1.dist-info/entry_points.txt
b3_data-0.2.1.dist-info/LICENSE
b3_data-0.2.1.dist-info/WHEEL
b3_data-0.2.1.dist-info/METADATA
b3_data-0.2.1.dist-info/RECORD
