Metadata-Version: 2.1
Name: b3-data
Version: 0.2.1
Summary: Download quote data from b3.com.br
License: MIT
Author: Wesley Batista
Requires-Python: >=3.7,<4.0
Classifier: License :: OSI Approved :: MIT License
Classifier: Programming Language :: Python :: 3
Classifier: Programming Language :: Python :: 3.7
Classifier: Programming Language :: Python :: 3.8
Classifier: Programming Language :: Python :: 3.9
Requires-Dist: click (>=7.1.2,<8.0.0)
Requires-Dist: requests (>=2.25.0,<3.0.0)
